{"data":{"page":{"title":"TREZOR: Window Blocked Before Confirming Transaction","slug":"troubleshooting/hardware-wallets/trezor/trezor-error-window-blocked","originalSlug":"troubleshooting/hardware-wallets/trezor/trezor-error-window-blocked","description":"Hardware Wallets","datePublished":"2015-07-15","dateModified":"2018-11-29","parent":{"__typename":"Category","title":"TREZOR Wallet"},"breadcrumbs":[{"title":"Troubleshooting Issues","slug":"troubleshooting"},{"title":"Hardware Wallets","slug":"troubleshooting/hardware-wallets"},{"title":"TREZOR Wallet","slug":"troubleshooting/hardware-wallets/trezor"},{"title":"TREZOR: Window Blocked Before Confirming Transaction","slug":"troubleshooting/hardware-wallets/trezor/trezor-error-window-blocked"}]},"file":{"childMarkdownRemark":{"html":"<blockquote>\n<p>I keep getting a message saying \"Window Blocked\" before confirming my transaction.</p>\n</blockquote>\n<p>When connecting to your TREZOR device, you need to ALLOW POP-UPS on MyCrypto.com.</p>\n<p>This allows information to safely be sent to your TREZOR device so that the device can sign the transaction and you can safely send the transaction via our infrastructure.</p>"}}},"pageContext":{"slug":"troubleshooting/hardware-wallets/trezor/trezor-error-window-blocked","file":"troubleshooting/hardware-wallets/trezor/trezor-error-window-blocked.md"}}